pyhooked/__init__.py
pyhooked-0.8.1.dist-info/DESCRIPTION.rst
pyhooked-0.8.1.dist-info/METADATA
pyhooked-0.8.1.dist-info/RECORD
pyhooked-0.8.1.dist-info/WHEEL
pyhooked-0.8.1.dist-info/metadata.json
pyhooked-0.8.1.dist-info/top_level.txt
