Metadata-Version: 2.0
Name: pyhooked
Version: 0.8.1
Summary: Pure Python hotkey hook, with thanks to pyHook, pywinauto, and pyhk
Home-page: https://github.com/ethanhs/hooked
Author: Ethan Smith
Author-email: ethan@ethanhs.me
License: UNKNOWN
Download-URL: https://github.com/ethanhs/pyhooked/tarball/0.8.1
Keywords: hotkey,shortcut,windows,keyboard,hooks,hook
Platform: UNKNOWN
